rtl/core_single/alu.vhd
library ieee;
use ieee.std_logic_1164.all;
use ieee.numeric_std.all;
use work.pkg_types.all;

entity alu is
  port(
    a, b : in  std_logic_vector(31 downto 0);
    op   : in  alu_op_t;
    y    : out std_logic_vector(31 downto 0)
  );
end entity;

architecture rtl of alu is
begin
  process(a,b,op)
    variable ru : unsigned(31 downto 0);
  begin
    case op is
      when ALU_ADD  => ru := unsigned(a) + unsigned(b);
      when ALU_SUB  => ru := unsigned(a) - unsigned(b);
      when ALU_AND  => ru := unsigned(a) and unsigned(b);
      when ALU_OR   => ru := unsigned(a) or  unsigned(b);
      when ALU_XOR  => ru := unsigned(a) xor unsigned(b);
      when ALU_SLL  => ru := shift_left(unsigned(a), to_integer(unsigned(b(4 downto 0))));
      when ALU_SRL  => ru := shift_right(unsigned(a), to_integer(unsigned(b(4 downto 0))));
      when ALU_SRA  => ru := unsigned(shift_right(signed(a), to_integer(unsigned(b(4 downto 0)))));
      when ALU_SLT  => ru := (others=>'0'); if signed(a) < signed(b) then ru(0):='1'; end if;
      when ALU_SLTU => ru := (others=>'0'); if unsigned(a) < unsigned(b) then ru(0):='1'; end if;
      when others   => ru := unsigned(a); -- PASS
    end case;
    y <= std_logic_vector(ru);
  end process;
end architecture;

rtl/core_single/regfile.vhd
library ieee;
use ieee.std_logic_1164.all;
use ieee.numeric_std.all;

entity regfile is
  port(
    clk    : in  std_logic;
    we     : in  std_logic;
    waddr  : in  std_logic_vector(4 downto 0);
    wdata  : in  std_logic_vector(31 downto 0);
    raddr1 : in  std_logic_vector(4 downto 0);
    raddr2 : in  std_logic_vector(4 downto 0);
    rdata1 : out std_logic_vector(31 downto 0);
    rdata2 : out std_logic_vector(31 downto 0)
  );
end entity;

architecture rtl of regfile is
  type reg_array is array (31 downto 0) of std_logic_vector(31 downto 0);
  signal regs : reg_array := (others => (others => '0'));
begin
  rdata1 <= (others=>'0') when raddr1 = "00000" else regs(to_integer(unsigned(raddr1)));
  rdata2 <= (others=>'0') when raddr2 = "00000" else regs(to_integer(unsigned(raddr2)));

  process(clk)
  begin
    if rising_edge(clk) then
      if we = '1' and waddr /= "00000" then
        regs(to_integer(unsigned(waddr))) <= wdata;
      end if;
    end if;
  end process;
end architecture;

rtl/core_single/control_simple.vhd
library ieee;
use ieee.std_logic_1164.all;
use ieee.numeric_std.all;
use work.pkg_types.all;
use work.pkg_isa.all;

entity control_simple is
  port(
    instr      : in  std_logic_vector(31 downto 0);
    alu_op     : out alu_op_t;
    reg_dst    : out std_logic;  -- 1=rd, 0=rt
    reg_we     : out std_logic;
    alu_src    : out std_logic;  -- 1=imm, 0=reg
    mem_cmd    : out mem_cmd_t;  -- NONE/LOAD/STORE
    mem_to_reg : out std_logic   -- 1=from MEM, 0=ALU
  );
end entity;

architecture rtl of control_simple is
  signal op : std_logic_vector(5 downto 0);
  signal fn : std_logic_vector(5 downto 0);
begin
  op <= instr(31 downto 26);
  fn <= instr(5 downto 0);

  process(op, fn)
  begin
    alu_op     <= ALU_ADD;
    reg_dst    <= '0';
    reg_we     <= '0';
    alu_src    <= '0';
    mem_cmd    <= MEM_NONE;
    mem_to_reg <= '0';

    if op = OPC_RTYPE then
      reg_dst <= '1';
      reg_we  <= '1';
      case fn is
        when FUNCT_ADD => alu_op <= ALU_ADD;
        when FUNCT_SUB => alu_op <= ALU_SUB;
        when FUNCT_AND => alu_op <= ALU_AND;
        when FUNCT_OR  => alu_op <= ALU_OR;
        when FUNCT_XOR => alu_op <= ALU_XOR;
        when others    => reg_we <= '0';
      end case;

    elsif op = OPC_ADDI then
      reg_we  <= '1';
      alu_src <= '1';
      alu_op  <= ALU_ADD;

    elsif op = OPC_LW then
      reg_we     <= '1';
      alu_src    <= '1';
      mem_cmd    <= MEM_LOAD;
      mem_to_reg <= '1';
      alu_op     <= ALU_ADD; -- base + offset

    elsif op = OPC_SW then
      reg_we  <= '0';
      alu_src <= '1';
      mem_cmd <= MEM_STORE;
      alu_op  <= ALU_ADD; -- base + offset

    else
      -- Unsupported in Week 1 → NOP
      null;
    end if;
  end process;
end architecture;

rtl/mem/mem_dual.vhd
library ieee;
use ieee.std_logic_1164.all;
use ieee.numeric_std.all;

entity mem_dual is
  generic(
    G_DEPTH_WORDS : integer := 1024
  );
  port(
    -- Port A: instruction (read-only)
    a_addr  : in  std_logic_vector(31 downto 0); -- byte address
    a_rdata : out std_logic_vector(31 downto 0);

    -- Port B: data (read/write)
    clk     : in  std_logic;
    b_we    : in  std_logic;
    b_addr  : in  std_logic_vector(31 downto 0); -- byte address
    b_wdata : in  std_logic_vector(31 downto 0);
    b_rdata : out std_logic_vector(31 downto 0)
  );
end entity;

architecture rtl of mem_dual is
  type mem_t is array (0 to G_DEPTH_WORDS-1) of std_logic_vector(31 downto 0);
  signal mem : mem_t := (others => (others => '0'));

  -- returns true if all bits are '0' or '1'
  function is_clean_slv(s: std_logic_vector) return boolean is
  begin
    for i in s'range loop
      if s(i) /= '0' and s(i) /= '1' then
        return false;
      end if;
    end loop;
    return true;
  end function;

  function word_index(addr: std_logic_vector(31 downto 0)) return integer is
  begin
    if not is_clean_slv(addr) then
      return -1; -- avoid to_integer on meta-values
    end if;
    return to_integer(unsigned(addr(31 downto 2))); -- word index
  end function;

begin
  -- Combinational read (Port A) — sensitive to address AND memory
  process(a_addr, mem)
    variable idx : integer;
  begin
    idx := word_index(a_addr);
    if idx >= 0 and idx < G_DEPTH_WORDS then
      a_rdata <= mem(idx);
    else
      a_rdata <= (others => '0');
    end if;
  end process;

  -- Combinational read (Port B) — sensitive to address AND memory
  process(b_addr, mem)
    variable idx : integer;
  begin
    idx := word_index(b_addr);
    if idx >= 0 and idx < G_DEPTH_WORDS then
      b_rdata <= mem(idx);
    else
      b_rdata <= (others => '0');
    end if;
  end process;

  -- Synchronous write (Port B)
  process(clk)
    variable idx : integer;
  begin
    if rising_edge(clk) then
      if b_we = '1' then
        idx := word_index(b_addr);
        if idx >= 0 and idx < G_DEPTH_WORDS then
          mem(idx) <= b_wdata;
        end if;
      end if;
    end if;
  end process;
end architecture;

rtl/core_single/core_single_top.vhd
library ieee;
use ieee.std_logic_1164.all;
use ieee.numeric_std.all;
use work.pkg_types.all;

entity core_single_top is
  port(
    clk     : in  std_logic;
    rst     : in  std_logic;
    dbg_r6  : out std_logic_vector(31 downto 0)
  );
end entity;

architecture rtl of core_single_top is
  component mem_dual
    generic(G_DEPTH_WORDS : integer := 1024);
    port(
      a_addr  : in  std_logic_vector(31 downto 0);
      a_rdata : out std_logic_vector(31 downto 0);
      clk     : in  std_logic;
      b_we    : in  std_logic;
      b_addr  : in  std_logic_vector(31 downto 0);
      b_wdata : in  std_logic_vector(31 downto 0);
      b_rdata : out std_logic_vector(31 downto 0)
    );
  end component;

  component regfile
    port(
      clk    : in  std_logic;
      we     : in  std_logic;
      waddr  : in  std_logic_vector(4 downto 0);
      wdata  : in  std_logic_vector(31 downto 0);
      raddr1 : in  std_logic_vector(4 downto 0);
      raddr2 : in  std_logic_vector(4 downto 0);
      rdata1 : out std_logic_vector(31 downto 0);
      rdata2 : out std_logic_vector(31 downto 0)
    );
  end component;

  component alu
    port(
      a, b : in  std_logic_vector(31 downto 0);
      op   : in  alu_op_t;
      y    : out std_logic_vector(31 downto 0)
    );
  end component;

  component control_simple
    port(
      instr      : in  std_logic_vector(31 downto 0);
      alu_op     : out alu_op_t;
      reg_dst    : out std_logic;
      reg_we     : out std_logic;
      alu_src    : out std_logic;
      mem_cmd    : out mem_cmd_t;
      mem_to_reg : out std_logic
    );
  end component;

  -- === VHDL-93 HEX HELPERS ===
  function nybble_to_char(n : std_logic_vector(3 downto 0)) return character is
    variable u : unsigned(3 downto 0);
  begin
    u := unsigned(n);
    if u < 10 then
      return character'val(character'pos('0') + to_integer(u));
    else
      return character'val(character'pos('A') + to_integer(u) - 10);
    end if;
  end function;

  function slv32_to_hex(s : std_logic_vector(31 downto 0)) return string is
    variable res : string(1 to 8);
    variable nib : std_logic_vector(3 downto 0);
  begin
    for i in 0 to 7 loop
      nib := s(31 - i*4 downto 28 - i*4);
      res(i+1) := nybble_to_char(nib);
    end loop;
    return res;
  end function;

  -- PC and instruction
  signal pc          : std_logic_vector(31 downto 0) := (others => '0');
  signal instr       : std_logic_vector(31 downto 0);
  signal mem_i_rdata : std_logic_vector(31 downto 0);

  -- Decode fields
  signal rs, rt, rd : std_logic_vector(4 downto 0);
  signal imm16      : std_logic_vector(15 downto 0);
  signal imm_sext   : std_logic_vector(31 downto 0);

  -- Control
  signal alu_op     : alu_op_t;
  signal reg_dst    : std_logic;
  signal reg_we     : std_logic;
  signal alu_src    : std_logic;
  signal mem_cmd    : mem_cmd_t;
  signal mem_to_reg : std_logic;

  -- Register file
  signal reg_waddr  : std_logic_vector(4 downto 0);
  signal reg_wdata  : std_logic_vector(31 downto 0);
  signal rs_data, rt_data : std_logic_vector(31 downto 0);

  -- ALU
  signal alu_b   : std_logic_vector(31 downto 0);
  signal alu_y   : std_logic_vector(31 downto 0);

  -- Data memory
  signal mem_d_rdata : std_logic_vector(31 downto 0);
  signal mem_we      : std_logic;
  signal mem_addr    : std_logic_vector(31 downto 0);
  signal mem_wdata   : std_logic_vector(31 downto 0);

  -- Debug
  signal r6_value : std_logic_vector(31 downto 0) := (others=>'0');

  -- Small inline ROM for first 9 words
  type rom_t is array (0 to 8) of std_logic_vector(31 downto 0);
  constant ROM : rom_t := (
    0 => x"20010001", -- addi $1,$0,1
    1 => x"20020002", -- addi $2,$0,2
    2 => x"20030003", -- addi $3,$0,3
    3 => x"00222020", -- add  $4,$1,$2
    4 => x"00832020", -- add  $4,$4,$3
    5 => x"20050004", -- addi $5,$0,4
    6 => x"00852020", -- add  $4,$4,$5   => $4 = 10
    7 => x"AC040100", -- sw   $4,0x0100($0)
    8 => x"8C060100"  -- lw   $6,0x0100($0)
  );

  function pc_to_index(p: std_logic_vector(31 downto 0)) return integer is
  begin
    if p(31 downto 9) /= (p(31 downto 9)'range => '0') then
      return -1;
    end if;
    return to_integer(unsigned(p(8 downto 2)));
  end function;

  signal instr_from_rom : std_logic_vector(31 downto 0);
  signal instr_sel_rom  : std_logic := '0';

begin
  -- PC
  process(clk)
  begin
    if rising_edge(clk) then
      if rst = '1' then
        pc <= (others => '0');
      else
        pc <= std_logic_vector(unsigned(pc) + 4);
      end if;
    end if;
  end process;

  -- Unified memory
  u_mem: mem_dual
    generic map(G_DEPTH_WORDS => 1024)
    port map(
      a_addr  => pc,
      a_rdata => mem_i_rdata,
      clk     => clk,
      b_we    => mem_we,
      b_addr  => mem_addr,
      b_wdata => mem_wdata,
      b_rdata => mem_d_rdata
    );

  -- ROM fetch
  process(pc)
    variable idx : integer;
  begin
    idx := pc_to_index(pc);
    if idx >= 0 and idx <= 8 then
      instr_from_rom <= ROM(idx);
      instr_sel_rom  <= '1';
    else
      instr_from_rom <= (others => '0');
      instr_sel_rom  <= '0';
    end if;
  end process;

  -- Single instruction driver
  instr <= instr_from_rom when instr_sel_rom = '1' else mem_i_rdata;

  -- DEBUG: IFETCH
  process(clk)
    variable shown : integer := 0;
  begin
    if rising_edge(clk) then
      if rst = '0' and shown < 20 then
        report "IFETCH pc=0x" & slv32_to_hex(pc) &
               " instr=0x" & slv32_to_hex(instr) severity note;
        shown := shown + 1;
      end if;
    end if;
  end process;

  -- Decode
  rs    <= instr(25 downto 21);
  rt    <= instr(20 downto 16);
  rd    <= instr(15 downto 11);
  imm16 <= instr(15 downto 0);
  imm_sext <= (31 downto 16 => imm16(15)) & imm16;

  -- Control
  u_ctl: control_simple
    port map(
      instr      => instr,
      alu_op     => alu_op,
      reg_dst    => reg_dst,
      reg_we     => reg_we,
      alu_src    => alu_src,
      mem_cmd    => mem_cmd,
      mem_to_reg => mem_to_reg
    );

  -- Regfile
  u_rf: regfile
    port map(
      clk    => clk,
      we     => reg_we,
      waddr  => reg_waddr,
      wdata  => reg_wdata,
      raddr1 => rs,
      raddr2 => rt,
      rdata1 => rs_data,
      rdata2 => rt_data
    );

  -- ALU
  alu_b <= imm_sext when alu_src = '1' else rt_data;
  u_alu: alu port map(a => rs_data, b => alu_b, op => alu_op, y => alu_y);

  -- Data memory
  mem_addr  <= alu_y;
  mem_wdata <= rt_data;
  mem_we    <= '1' when mem_cmd = MEM_STORE else '0';

  -- DEBUG: STORE
  process(clk)
  begin
    if rising_edge(clk) then
      if rst = '0' and mem_we = '1' then
        report "STORE  addr=0x" & slv32_to_hex(mem_addr) &
               " data=0x" & slv32_to_hex(mem_wdata) severity note;
      end if;
    end if;
  end process;

  -- Writeback
  reg_waddr <= rd when reg_dst = '1' else rt;
  reg_wdata <= mem_d_rdata when mem_to_reg = '1' else alu_y;

  -- DEBUG: WB
  process(clk)
  begin
    if rising_edge(clk) then
      if rst = '0' and reg_we = '1' then
        report "WB     r" & integer'image(to_integer(unsigned(reg_waddr))) &
               " = 0x" & slv32_to_hex(reg_wdata) severity note;
      end if;
    end if;
  end process;

  -- Capture last write to $6
  process(clk)
  begin
    if rising_edge(clk) then
      if reg_we = '1' and reg_waddr = "00110" then
        r6_value <= reg_wdata;
      end if;
    end if;
  end process;

  dbg_r6 <= r6_value;

end architecture;

sim/single/tb_core_single.vhd
library ieee;
use ieee.std_logic_1164.all;
use ieee.numeric_std.all;

entity tb_core_single is end;
architecture tb of tb_core_single is
  component core_single_top
    port(
      clk    : in  std_logic;
      rst    : in  std_logic;
      dbg_r6 : out std_logic_vector(31 downto 0)
    );
  end component;

  signal clk, rst : std_logic := '0';
  signal dbg_r6   : std_logic_vector(31 downto 0);

begin
  -- 100 MHz nominal (10 ns period)
  clk <= not clk after 5 ns;

  DUT: core_single_top
    port map(
      clk    => clk,
      rst    => rst,
      dbg_r6 => dbg_r6
    );

  stim: process
  begin
    rst <= '1'; wait for 40 ns;
    rst <= '0';

    -- Program has 9 instructions; give enough cycles
    wait for 300 ns;

    -- Expect 10 (0x0000000A) in $6
    assert dbg_r6 = x"0000000A"
      report "FAIL: $6 is " & integer'image(to_integer(unsigned(dbg_r6))) &
             ", expected 10"
      severity failure;

    report "TB finished OK" severity note;

    -- No stop here; let --stop-time terminate the sim with exit code 0
    wait;
  end process;
end architecture;

sim/single/waves.vcd
$date
  Sat Oct  4 20:11:39 2025
$end
$version
  GHDL v0
$end
$timescale
  1 fs
$end
$scope module standard $end
$upscope $end
$scope module std_logic_1164 $end
$upscope $end
$scope module numeric_std $end
$upscope $end
$scope module pkg_types $end
$upscope $end
$scope module pkg_isa $end
$upscope $end
$scope module tb_core_single $end
$var reg 1 ! clk $end
$var reg 1 " rst $end
$var reg 32 # dbg_r6[31:0] $end
$scope module dut $end
$var reg 1 $ clk $end
$var reg 1 % rst $end
$var reg 32 & dbg_r6[31:0] $end
$var reg 32 ' pc[31:0] $end
$var reg 32 ( instr[31:0] $end
$var reg 32 ) mem_i_rdata[31:0] $end
$var reg 5 * rs[4:0] $end
$var reg 5 + rt[4:0] $end
$var reg 5 , rd[4:0] $end
$var reg 16 - imm16[15:0] $end
$var reg 32 . imm_sext[31:0] $end
$comment alu_op is not handled $end
$var reg 1 / reg_dst $end
$var reg 1 0 reg_we $end
$var reg 1 1 alu_src $end
$comment mem_cmd is not handled $end
$var reg 1 2 mem_to_reg $end
$var reg 5 3 reg_waddr[4:0] $end
$var reg 32 4 reg_wdata[31:0] $end
$var reg 32 5 rs_data[31:0] $end
$var reg 32 6 rt_data[31:0] $end
$var reg 32 7 alu_b[31:0] $end
$var reg 32 8 alu_y[31:0] $end
$var reg 32 9 mem_d_rdata[31:0] $end
$var reg 1 : mem_we $end
$var reg 32 ; mem_addr[31:0] $end
$var reg 32 < mem_wdata[31:0] $end
$var reg 32 = r6_value[31:0] $end
$var reg 32 > instr_from_rom[31:0] $end
$var reg 1 ? instr_sel_rom $end
$scope module u_mem $end
$var reg 32 @ a_addr[31:0] $end
$var reg 32 A a_rdata[31:0] $end
$var reg 1 B clk $end
$var reg 1 C b_we $end
$var reg 32 D b_addr[31:0] $end
$var reg 32 E b_wdata[31:0] $end
$var reg 32 F b_rdata[31:0] $end
$comment mem is not handled $end
$upscope $end
$scope module u_ctl $end
$var reg 32 G instr[31:0] $end
$comment alu_op is not handled $end
$var reg 1 H reg_dst $end
$var reg 1 I reg_we $end
$var reg 1 J alu_src $end
$comment mem_cmd is not handled $end
$var reg 1 K mem_to_reg $end
$var reg 6 L op[5:0] $end
$var reg 6 M fn[5:0] $end
$upscope $end
$scope module u_rf $end
$var reg 1 N clk $end
$var reg 1 O we $end
$var reg 5 P waddr[4:0] $end
$var reg 32 Q wdata[31:0] $end
$var reg 5 R raddr1[4:0] $end
$var reg 5 S raddr2[4:0] $end
$var reg 32 T rdata1[31:0] $end
$var reg 32 U rdata2[31:0] $end
$comment regs is not handled $end
$upscope $end
$scope module u_alu $end
$var reg 32 V a[31:0] $end
$var reg 32 W b[31:0] $end
$comment op is not handled $end
$var reg 32 X y[31:0] $end
$upscope $end
$upscope $end
$upscope $end
$enddefinitions $end
#0
0!
1"
b00000000000000000000000000000000 #
0$
1%
b00000000000000000000000000000000 &
b00000000000000000000000000000000 '
b00100000000000010000000000000001 (
b00000000000000000000000000000000 )
b00000 *
b00001 +
b00000 ,
b0000000000000001 -
b00000000000000000000000000000001 .
0/
10
11
02
b00001 3
b00000000000000000000000000000001 4
b00000000000000000000000000000000 5
b00000000000000000000000000000000 6
b00000000000000000000000000000001 7
b00000000000000000000000000000001 8
b00000000000000000000000000000000 9
0:
b00000000000000000000000000000001 ;
b00000000000000000000000000000000 <
b00000000000000000000000000000000 =
b00100000000000010000000000000001 >
1?
b00000000000000000000000000000000 @
b00000000000000000000000000000000 A
0B
0C
b00000000000000000000000000000001 D
b00000000000000000000000000000000 E
b00000000000000000000000000000000 F
b00100000000000010000000000000001 G
0H
1I
1J
0K
b001000 L
b000001 M
0N
1O
b00001 P
b00000000000000000000000000000001 Q
b00000 R
b00001 S
b00000000000000000000000000000000 T
b00000000000000000000000000000000 U
b00000000000000000000000000000000 V
b00000000000000000000000000000001 W
b00000000000000000000000000000001 X
#5000000
1!
1$
b00000000000000000000000000000001 6
b00000000000000000000000000000001 <
1B
b00000000000000000000000000000001 E
1N
b00000000000000000000000000000001 U
#10000000
0!
0$
0B
0N
#15000000
1!
1$
1B
1N
#20000000
0!
0$
0B
0N
#25000000
1!
1$
1B
1N
#30000000
0!
0$
0B
0N
#35000000
1!
1$
1B
1N
#40000000
0!
0"
0$
0%
0B
0N
#45000000
1!
1$
b00000000000000000000000000000100 '
b00100000000000100000000000000010 (
b00010 +
b0000000000000010 -
b00000000000000000000000000000010 .
b00010 3
b00000000000000000000000000000010 4
b00000000000000000000000000000000 6
b00000000000000000000000000000010 7
b00000000000000000000000000000010 8
b00000000000000000000000000000010 ;
b00000000000000000000000000000000 <
b00100000000000100000000000000010 >
b00000000000000000000000000000100 @
1B
b00000000000000000000000000000010 D
b00000000000000000000000000000000 E
b00100000000000100000000000000010 G
1I
1J
b000010 M
1N
b00010 P
b00000000000000000000000000000010 Q
b00010 S
b00000000000000000000000000000000 U
b00000000000000000000000000000010 W
b00000000000000000000000000000010 X
#50000000
0!
0$
0B
0N
#55000000
1!
1$
b00000000000000000000000000001000 '
b00100000000000110000000000000011 (
b00011 +
b0000000000000011 -
b00000000000000000000000000000011 .
b00011 3
b00000000000000000000000000000011 4
b00000000000000000000000000000000 6
b00000000000000000000000000000011 7
b00000000000000000000000000000011 8
b00000000000000000000000000000011 ;
b00000000000000000000000000000000 <
b00100000000000110000000000000011 >
b00000000000000000000000000001000 @
1B
b00000000000000000000000000000011 D
b00000000000000000000000000000000 E
b00100000000000110000000000000011 G
1I
1J
b000011 M
1N
b00011 P
b00000000000000000000000000000011 Q
b00011 S
b00000000000000000000000000000000 U
b00000000000000000000000000000011 W
b00000000000000000000000000000011 X
#60000000
0!
0$
0B
0N
#65000000
1!
1$
b00000000000000000000000000001100 '
b00000000001000100010000000100000 (
b00001 *
b00010 +
b00100 ,
b0010000000100000 -
b00000000000000000010000000100000 .
1/
01
b00100 3
b00000000000000000000000000000011 4
b00000000000000000000000000000001 5
b00000000000000000000000000000010 6
b00000000000000000000000000000010 7
b00000000000000000000000000000011 8
b00000000000000000000000000000011 ;
b00000000000000000000000000000010 <
b00000000001000100010000000100000 >
b00000000000000000000000000001100 @
1B
b00000000000000000000000000000011 D
b00000000000000000000000000000010 E
b00000000001000100010000000100000 G
1H
1I
0J
b000000 L
b100000 M
1N
b00100 P
b00000000000000000000000000000011 Q
b00001 R
b00010 S
b00000000000000000000000000000001 T
b00000000000000000000000000000010 U
b00000000000000000000000000000001 V
b00000000000000000000000000000010 W
b00000000000000000000000000000011 X
#70000000
0!
0$
0B
0N
#75000000
1!
1$
b00000000000000000000000000010000 '
b00000000100000110010000000100000 (
b00100 *
b00011 +
b00000000000000000000000000000110 4
b00000000000000000000000000000011 5
b00000000000000000000000000000011 6
b00000000000000000000000000000011 7
b00000000000000000000000000000110 8
b00000000000000000000000000000110 ;
b00000000000000000000000000000011 <
b00000000100000110010000000100000 >
b00000000000000000000000000010000 @
1B
b00000000000000000000000000000110 D
b00000000000000000000000000000011 E
b00000000100000110010000000100000 G
1N
b00000000000000000000000000000110 Q
b00100 R
b00011 S
b00000000000000000000000000000011 T
b00000000000000000000000000000011 U
b00000000000000000000000000000011 V
b00000000000000000000000000000011 W
b00000000000000000000000000000110 X
#80000000
0!
0$
0B
0N
#85000000
1!
1$
b00000000000000000000000000010100 '
b00100000000001010000000000000100 (
b00000 *
b00101 +
b00000 ,
b0000000000000100 -
b00000000000000000000000000000100 .
0/
11
b00101 3
b00000000000000000000000000000100 4
b00000000000000000000000000000000 5
b00000000000000000000000000000000 6
b00000000000000000000000000000100 7
b00000000000000000000000000000100 8
b00000000000000000000000000000100 ;
b00000000000000000000000000000000 <
b00100000000001010000000000000100 >
b00000000000000000000000000010100 @
1B
b00000000000000000000000000000100 D
b00000000000000000000000000000000 E
b00100000000001010000000000000100 G
0H
1I
1J
b001000 L
b000100 M
1N
b00101 P
b00000000000000000000000000000100 Q
b00000 R
b00101 S
b00000000000000000000000000000000 T
b00000000000000000000000000000000 U
b00000000000000000000000000000000 V
b00000000000000000000000000000100 W
b00000000000000000000000000000100 X
#90000000
0!
0$
0B
0N
#95000000
1!
1$
b00000000000000000000000000011000 '
b00000000100001010010000000100000 (
b00100 *
b00100 ,
b0010000000100000 -
b00000000000000000010000000100000 .
1/
01
b00100 3
b00000000000000000000000000001010 4
b00000000000000000000000000000110 5
b00000000000000000000000000000100 6
b00000000000000000000000000001010 8
b00000000000000000000000000001010 ;
b00000000000000000000000000000100 <
b00000000100001010010000000100000 >
b00000000000000000000000000011000 @
1B
b00000000000000000000000000001010 D
b00000000000000000000000000000100 E
b00000000100001010010000000100000 G
1H
1I
0J
b000000 L
b100000 M
1N
b00100 P
b00000000000000000000000000001010 Q
b00100 R
b00000000000000000000000000000110 T
b00000000000000000000000000000100 U
b00000000000000000000000000000110 V
b00000000000000000000000000001010 X
#100000000
0!
0$
0B
0N
#105000000
1!
1$
b00000000000000000000000000011100 '
b10101100000001000000000100000000 (
b00000 *
b00100 +
b00000 ,
b0000000100000000 -
b00000000000000000000000100000000 .
0/
00
11
b00100 3
b00000000000000000000000100000000 4
b00000000000000000000000000000000 5
b00000000000000000000000000001010 6
b00000000000000000000000100000000 7
b00000000000000000000000100000000 8
1:
b00000000000000000000000100000000 ;
b00000000000000000000000000001010 <
b10101100000001000000000100000000 >
b00000000000000000000000000011100 @
1B
1C
b00000000000000000000000100000000 D
b00000000000000000000000000001010 E
b10101100000001000000000100000000 G
0H
0I
1J
b101011 L
b000000 M
1N
0O
b00100 P
b00000000000000000000000100000000 Q
b00000 R
b00100 S
b00000000000000000000000000000000 T
b00000000000000000000000000001010 U
b00000000000000000000000000000000 V
b00000000000000000000000100000000 W
b00000000000000000000000100000000 X
#110000000
0!
0$
0B
0N
#115000000
1!
1$
b00000000000000000000000000100000 '
b10001100000001100000000100000000 (
b00110 +
10
12
b00110 3
b00000000000000000000000000001010 4
b00000000000000000000000000000000 6
b00000000000000000000000000001010 9
0:
b00000000000000000000000000000000 <
b10001100000001100000000100000000 >
b00000000000000000000000000100000 @
1B
0C
b00000000000000000000000000000000 E
b00000000000000000000000000001010 F
b10001100000001100000000100000000 G
1I
1J
1K
b100011 L
1N
1O
b00110 P
b00000000000000000000000000001010 Q
b00110 S
b00000000000000000000000000000000 U
#120000000
0!
0$
0B
0N
#125000000
1!
b00000000000000000000000000001010 #
1$
b00000000000000000000000000001010 &
b00000000000000000000000000100100 '
b00000000000000000000000000000000 (
b00000 +
b0000000000000000 -
b00000000000000000000000000000000 .
1/
00
01
02
b00000 3
b00000000000000000000000000000000 4
b00000000000000000000000000000000 6
b00000000000000000000000000000000 7
b00000000000000000000000000000000 8
b00000000000000000000000000000000 9
b00000000000000000000000000000000 ;
b00000000000000000000000000000000 <
b00000000000000000000000000001010 =
b00000000000000000000000000000000 >
0?
b00000000000000000000000000100100 @
1B
b00000000000000000000000000000000 D
b00000000000000000000000000000000 E
b00000000000000000000000000000000 F
b00000000000000000000000000000000 G
1H
0I
0J
0K
b000000 L
1N
0O
b00000 P
b00000000000000000000000000000000 Q
b00000 S
b00000000000000000000000000000000 U
b00000000000000000000000000000000 W
b00000000000000000000000000000000 X
#130000000
0!
0$
0B
0N
#135000000
1!
1$
b00000000000000000000000000101000 '
b00000000000000000000000000101000 @
1B
1N
#140000000
0!
0$
0B
0N
#145000000
1!
1$
b00000000000000000000000000101100 '
b00000000000000000000000000101100 @
1B
1N
#150000000
0!
0$
0B
0N
#155000000
1!
1$
b00000000000000000000000000110000 '
b00000000000000000000000000110000 @
1B
1N
#160000000
0!
0$
0B
0N
#165000000
1!
1$
b00000000000000000000000000110100 '
b00000000000000000000000000110100 @
1B
1N
#170000000
0!
0$
0B
0N
#175000000
1!
1$
b00000000000000000000000000111000 '
b00000000000000000000000000111000 @
1B
1N
#180000000
0!
0$
0B
0N
#185000000
1!
1$
b00000000000000000000000000111100 '
b00000000000000000000000000111100 @
1B
1N
#190000000
0!
0$
0B
0N
#195000000
1!
1$
b00000000000000000000000001000000 '
b00000000000000000000000001000000 @
1B
1N
#200000000
0!
0$
0B
0N
#205000000
1!
1$
b00000000000000000000000001000100 '
b00000000000000000000000001000100 @
1B
1N
#210000000
0!
0$
0B
0N
#215000000
1!
1$
b00000000000000000000000001001000 '
b00000000000000000000000001001000 @
1B
1N
#220000000
0!
0$
0B
0N
#225000000
1!
1$
b00000000000000000000000001001100 '
b00000000000000000000000001001100 @
1B
1N
#230000000
0!
0$
0B
0N
#235000000
1!
1$
b00000000000000000000000001010000 '
b00000000000000000000000001010000 @
1B
1N
#240000000
0!
0$
0B
0N
#245000000
1!
1$
b00000000000000000000000001010100 '
b00000000000000000000000001010100 @
1B
1N
#250000000
0!
0$
0B
0N
#255000000
1!
1$
b00000000000000000000000001011000 '
b00000000000000000000000001011000 @
1B
1N
#260000000
0!
0$
0B
0N
#265000000
1!
1$
b00000000000000000000000001011100 '
b00000000000000000000000001011100 @
1B
1N
#270000000
0!
0$
0B
0N
#275000000
1!
1$
b00000000000000000000000001100000 '
b00000000000000000000000001100000 @
1B
1N
#280000000
0!
0$
0B
0N
#285000000
1!
1$
b00000000000000000000000001100100 '
b00000000000000000000000001100100 @
1B
1N
#290000000
0!
0$
0B
0N
#295000000
1!
1$
b00000000000000000000000001101000 '
b00000000000000000000000001101000 @
1B
1N
#300000000
0!
0$
0B
0N
#305000000
1!
1$
b00000000000000000000000001101100 '
b00000000000000000000000001101100 @
1B
1N
#310000000
0!
0$
0B
0N
#315000000
1!
1$
b00000000000000000000000001110000 '
b00000000000000000000000001110000 @
1B
1N
#320000000
0!
0$
0B
0N
#325000000
1!
1$
b00000000000000000000000001110100 '
b00000000000000000000000001110100 @
1B
1N
#330000000
0!
0$
0B
0N
#335000000
1!
1$
b00000000000000000000000001111000 '
b00000000000000000000000001111000 @
1B
1N
#340000000
0!
0$
0B
0N
#345000000
1!
1$
b00000000000000000000000001111100 '
b00000000000000000000000001111100 @
1B
1N
#350000000
0!
0$
0B
0N
#355000000
1!
1$
b00000000000000000000000010000000 '
b00000000000000000000000010000000 @
1B
1N
#360000000
0!
0$
0B
0N
#365000000
1!
1$
b00000000000000000000000010000100 '
b00000000000000000000000010000100 @
1B
1N
#370000000
0!
0$
0B
0N
#375000000
1!
1$
b00000000000000000000000010001000 '
b00000000000000000000000010001000 @
1B
1N
#380000000
0!
0$
0B
0N
#385000000
1!
1$
b00000000000000000000000010001100 '
b00000000000000000000000010001100 @
1B
1N
#390000000
0!
0$
0B
0N
#395000000
1!
1$
b00000000000000000000000010010000 '
b00000000000000000000000010010000 @
1B
1N
#400000000
0!
0$
0B
0N
#405000000
1!
1$
b00000000000000000000000010010100 '
b00000000000000000000000010010100 @
1B
1N
#410000000
0!
0$
0B
0N
#415000000
1!
1$
b00000000000000000000000010011000 '
b00000000000000000000000010011000 @
1B
1N
#420000000
0!
0$
0B
0N
#425000000
1!
1$
b00000000000000000000000010011100 '
b00000000000000000000000010011100 @
1B
1N
#430000000
0!
0$
0B
0N
#435000000
1!
1$
b00000000000000000000000010100000 '
b00000000000000000000000010100000 @
1B
1N
#440000000
0!
0$
0B
0N
#445000000
1!
1$
b00000000000000000000000010100100 '
b00000000000000000000000010100100 @
1B
1N
#450000000
0!
0$
0B
0N
#455000000
1!
1$
b00000000000000000000000010101000 '
b00000000000000000000000010101000 @
1B
1N
#460000000
0!
0$
0B
0N
#465000000
1!
1$
b00000000000000000000000010101100 '
b00000000000000000000000010101100 @
1B
1N
#470000000
0!
0$
0B
0N
